Workbook
Name rendimento_mensal_config: APP!$F$22

Sheet APP
B20: CONFIGURAÇÕES
B21: Salário | F21: 5000
B22: Rendimento Atual | F22: 0.01
B23: Investimento Sugerido | F23: 0.3
B25: INVESTIMENTO MENSAL
B26: Quanto investir por mês? | F26: 900
B27: Por quantos anos? | F27: 5
B28: Qual a taxa de rendimento mensal? | F28: 0.0108
B29: Patrimônio acumulado: | F29: =FV(rendimento_mensal_config,F27*12,F26*-1) -> 73502.703
B30: Dividendos mensais: | F30: =F29*F28 -> 793.82919
B32: CENÁRIOS | F32: Patrimonio | I32: Dividendo
B33: Quanto em 2 anos? | F33: =FV(F28,2*12,F26*-1) -> 24507.777 | I33: =F33*$F$22 -> 245.07777
B34: Quanto em 5 anos? | F34: =FV(F28,5*12,F26*-1) -> 75423.617 | I34: =F34*$F$22 -> 754.23617
B35: Quanto em 10 anos? | F35: =FV(F28,10*12,F26*-1) -> 219111.9 | I35: =F35*$F$22 -> 2191.119
B36: Quanto em 20 anos? | F36: =FV(F28,20*12,F26*-1) -> 1014344.1 | I36: =F36*$F$22 -> 10143.441
B37: Quanto em 30 anos? | F37: =FV(F28,30*12,F26*-1) -> 3900514.3 | I37: =F37*$F$22 -> 39005.143
B39: PERFIL | H39: Agressivo
B40: VALOR A SER INVESTIDO POR MÊS | H40: =F26 -> 900
B42: TIPO DE FII | H42: PERCENTUAL SUGERIDO | I42: VALOR
B43: PAPEL | H43: =VLOOKUP($H$39&"-"&B43,Conditions!$E:$H,4,FALSE) -> 0.5 | I43: =H43*$H$40 -> 450
B44: TIJOLO | H44: =VLOOKUP($H$39&"-"&B44,Conditions!$E:$H,4,FALSE) -> 0.1 | I44: =H44*$H$40 -> 90
B45: HÍBRIDOS | H45: =VLOOKUP($H$39&"-"&B45,Conditions!$E:$H,4,FALSE) -> 0.05 | I45: =H45*$H$40 -> 45
B46: FOFs | H46: =VLOOKUP($H$39&"-"&B46,Conditions!$E:$H,4,FALSE) -> 0.05 | I46: =H46*$H$40 -> 45
B47: DESENVOLVIMENTO | H47: =VLOOKUP($H$39&"-"&B47,Conditions!$E:$H,4,FALSE) -> 0.2 | I47: =H47*$H$40 -> 180
B48: HOTELARIAS | H48: =VLOOKUP($H$39&"-"&B48,Conditions!$E:$H,4,FALSE) -> 0.1 | I48: =H48*$H$40 -> 90
B49: TOTAL | H49: =SUM(H43:H48) -> 1 | I49: =SUM(I43:I48) -> 900

Sheet Conditions
E5: CHAVE | F5: Perfil | G5: TIPO DE FII | H5: Percentual
E6: =F6&"-"&G6 -> Conservador-PAPEL | F6: Conservador | G6: PAPEL | H6: 0.3
E7: =F7&"-"&G7 -> Conservador-TIJOLO | F7: Conservador | G7: TIJOLO | H7: 0.5
E8: =F8&"-"&G8 -> Conservador-HÍBRIDOS | F8: Conservador | G8: HÍBRIDOS | H8: 0.1
E9: =F9&"-"&G9 -> Conservador-FOFs | F9: Conservador | G9: FOFs | H9: 0.1
E10: =F10&"-"&G10 -> Conservador-DESENVOLVIMENTO | F10: Conservador | G10: DESENVOLVIMENTO | H10: 0
E11: =F11&"-"&G11 -> Conservador-HOTELARIAS | F11: Conservador | G11: HOTELARIAS | H11: 0
E12: =F12&"-"&G12 -> Moderado-PAPEL | F12: Moderado | G12: PAPEL | H12: 0.32
E13: =F13&"-"&G13 -> Moderado-TIJOLO | F13: Moderado | G13: TIJOLO | H13: 0.4
E14: =F14&"-"&G14 -> Moderado-HÍBRIDOS | F14: Moderado | G14: HÍBRIDOS | H14: 0.08
E15: =F15&"-"&G15 -> Moderado-FOFs | F15: Moderado | G15: FOFs | H15: 0.1
E16: =F16&"-"&G16 -> Moderado-DESENVOLVIMENTO | F16: Moderado | G16: DESENVOLVIMENTO | H16: 0
E17: =F17&"-"&G17 -> Moderado-HOTELARIAS | F17: Moderado | G17: HOTELARIAS | H17: 0.1
... E23: =F23&"-"&G23 -> Agressivo-HOTELARIAS | F23: Agressivo | G23: HOTELARIAS | H23: 0.1
